{"paths":{},"types":[],"uuids":["49U5ywOJNFmrMQfMG39tM1","71VhFCTINJM6/Ky3oX9nBT","8aVGk1cNRC0qBRjQ528oAI","99FwsL0hBG8bITfZ4/IwmK","9eKuUH+uVFEZQL8uRvgbeQ","a5qeFvDvdG86ppVktlMtP2","b4P/PCArtIdIH38t6mlw8Y","bcSQdUxVFJLqWDHFyN4vRI","c59gxiHsVIZZpbJbPscPJH","cf73jxyN9Jt47QTJU6ziYh","e8Ueib+qJEhL6mXAHdnwbi","07gsmHnGFNhqlHEXi1GHxG","093Qfqq5NPFJsm1f1XB701","0bPDtzZJ9JOIqAVDeAId+R","0c/TV5XCtKp7ebJGJBV61X","13kH3waxtB1JGn/6zsphn+","19hTHm0TlDEadP/7clqwi1","29FYIk+N1GYaeWH/q1NxQO","2at1O+u3dO0oYHKMCqV8Sp","3ffW8Ujj9DLKU3CcjH4Dt2","3fwJJcLVdLcow6mIN+kutz","45LsejdB1GlKSK2aoEWbfC","4bnpSAtadObJzPuAmnwKRw","58wMPk3pFEoLCt+E6KvWqs","64kU/zj1JO/bUQ35mfMvbl","675ovJ2tVK2aLYfgPUWOMv","76HhUJTNFEjZlxthHHkIqH","8855/VlrRKd6H0MSRnFxAU","92QV0kmqxMKKyWTU7sbjgQ","97IlIGAFBGc5voL61Ey3Tb","9dlIDmmJ9NN61JQN58rb8O","a0UeaF1pVKDppTfqkvrKr2","a5zLHwCmZM0bEySy+feCSQ","a6gpjuKplBJ5gd0Lq+fTrn","b3Typ/PPJBx53JjNtjE+hY","c5qZYKjaROnZvj++kTtG9b","d7d9XnsuZNrKbrkqU2LY6a","dap9Cet8dHeJ0vai58ZUcV","dbIbeEFA5ArobsOux88BlG","ddq4gs1H5LYZ8KRhDX5cdq","e8fW9810BIVYjLuVwsXFrU","e97GVMl6JHh5Ml5qEDdSGa","ebL9vRcbNGmYHrJx50hSqD","f0BIwQ8D5Ml7nTNQbh1YlS","f8smjXcFFET5ZRjanRM5HZ","fa7k4BFYZBobtg/c9Tkr0A","fdApTcWPZKEJzne/Yqp/u3"],"scenes":{"db://assets/menu/menu.fire":2},"redirect":[],"deps":[],"packs":{"078257804":[11,12,13,14,15,16,17,18,19,20,21,0,22,23,24,25,26,27,2,28,29,30,4,31,32,33,34,35,36,37,38,39,40,41,42,43,44,45,46],"0a96bdedb":[1,3,5,6,7,8,9,10]},"name":"menu","importBase":"import","nativeBase":"native","debug":false,"isZip":false,"encrypted":false,"versions":{"import":["078257804","7c6f3","0a96bdedb","fc990"],"native":[0,"f45ec",1,"c06a9",3,"d1118",4,"90d17",5,"a6e5e",6,"83fcc",7,"79fa9",8,"03bcf",9,"a4b59",10,"90cf4"]}}